speedybot/__init__.py
speedybot/speedybot.py
speedybot/speedycard.py
speedybot-0.6.2.dist-info/METADATA
speedybot-0.6.2.dist-info/WHEEL
speedybot-0.6.2.dist-info/RECORD
