Metadata-Version: 2.1
Name: speedybot
Version: 0.6.2
Summary: Next-gen conversation design tooling, makes it speedy and easy to send messages
Home-page: https://github.com/valgaze/speedybot-python
Keywords: bot,speedybot,adaptive cards
Author: Victor Algaze
Author-email: valgaze@gmail.com
Requires-Python: >=3.9,<4.0
Classifier: Programming Language :: Python :: 3
Classifier: Programming Language :: Python :: 3.9
Classifier: Programming Language :: Python :: 3.10
Classifier: Programming Language :: Python :: 3.11
Requires-Dist: requests (>=2.31.0,<3.0.0)
Project-URL: Repository, https://github.com/valgaze/speedybot-python
